globvar/__init__.py
globvar-1.0.0.dist-info/LICENSE
globvar-1.0.0.dist-info/METADATA
globvar-1.0.0.dist-info/WHEEL
globvar-1.0.0.dist-info/top_level.txt
globvar-1.0.0.dist-info/RECORD
